m_test_v11-0.1.3.dist-info/METADATA
m_test_v11-0.1.3.dist-info/WHEEL
m_test_v11-0.1.3.dist-info/entry_points.txt
m_test_v11/__init__.py
m_test_v11-0.1.3.dist-info/RECORD
